[
  {
    "question_text": "Which of the following is NOT one of the axioms of probability in the axiomatic approach?",
    "type": "MCQ",
    "difficulty": "Easy",
    "options": [
      "P(E) ≥ 0 for any event E",
      "P(S) = 1 for sample space S",
      "P(A ∪ B) = P(A) + P(B) for any events A and B",
      "For mutually exclusive events A and B, P(A ∪ B) = P(A) + P(B)"
    ],
    "correct_answer": "P(A ∪ B) = P(A) + P(B) for any events A and B",
    "explanation": "The axioms state that: (i) P(E) ≥ 0 for any event E, (ii) P(S) = 1, and (iii) if events are mutually exclusive then P(A ∪ B) = P(A) + P(B). The property P(A ∪ B) = P(A) + P(B) holds only for mutually exclusive events, not for any events.",
    "topic": "Axiomatic Approach to Probability",
    "bloom_level": "Remember",
    "source": "generated",
    "chapter_id": "kemh114",
    "section_id": "04_section_14_2",
    "question_id": "cbse_xi_kemh1dd_c114_gen016"
  },
  {
    "question_text": "Consider a sample space S = {ω₁, ω₂, ω₃, ω₄}. Which of the following assignments of probabilities is valid?",
    "type": "MCQ",
    "difficulty": "Medium",
    "options": [
      "P(ω₁)=0.2, P(ω₂)=0.3, P(ω₃)=0.3, P(ω₄)=0.1",
      "P(ω₁)=0.25, P(ω₂)=0.25, P(ω₃)=0.25, P(ω₄)=0.25",
      "P(ω₁)=0.5, P(ω₂)=0.3, P(ω₃)=0.1, P(ω₄)=0.2",
      "P(ω₁)=0.1, P(ω₂)=0.1, P(ω₃)=-0.1, P(ω₄)=0.9"
    ],
    "correct_answer": "P(ω₁)=0.25, P(ω₂)=0.25, P(ω₃)=0.25, P(ω₄)=0.25",
    "explanation": "A valid probability assignment requires that each probability is between 0 and 1 and the sum of all probabilities equals 1. Option (b) meets both conditions (0.25 each, sum equals 1), whereas the others violate either the sum requirement or the non-negativity condition.",
    "topic": "Axiomatic Approach to Probability",
    "bloom_level": "Understand",
    "source": "generated",
    "chapter_id": "kemh114",
    "section_id": "04_section_14_2",
    "question_id": "cbse_xi_kemh1dd_c114_gen017"
  },
  {
    "question_text": "If events A and B are mutually exclusive, then what is P(A ∪ B)?",
    "type": "MCQ",
    "difficulty": "Easy",
    "options": [
      "P(A) + P(B)",
      "P(A) + P(B) - P(A ∩ B)",
      "P(A) * P(B)",
      "1 - [P(A) + P(B)]"
    ],
    "correct_answer": "P(A) + P(B)",
    "explanation": "For mutually exclusive events, by definition, A ∩ B = ∅ and hence P(A ∩ B) = 0. Therefore, P(A ∪ B) = P(A) + P(B).",
    "topic": "Addition Rule in Probability",
    "bloom_level": "Remember",
    "source": "generated",
    "chapter_id": "kemh114",
    "section_id": "04_section_14_2",
    "question_id": "cbse_xi_kemh1dd_c114_gen018"
  },
  {
    "question_text": "In a coin toss experiment where outcomes have different probabilities, if event E is defined as 'both tosses yield the same result', which of the following expressions correctly represents P(E) when E = {HH, TT}?",
    "type": "MCQ",
    "difficulty": "Medium",
    "options": [
      "P(E) = P(H) + P(T)",
      "P(E) = P(HH) + P(TT)",
      "P(E) = P(HH) - P(TT)",
      "P(E) = P(H) * P(T)"
    ],
    "correct_answer": "P(E) = P(HH) + P(TT)",
    "explanation": "Since event E contains the outcomes 'HH' and 'TT', the probability of E is the sum of the probabilities of these two disjoint events: P(E) = P(HH) + P(TT).",
    "topic": "Probability of an Event",
    "bloom_level": "Apply",
    "source": "generated",
    "chapter_id": "kemh114",
    "section_id": "04_section_14_2",
    "question_id": "cbse_xi_kemh1dd_c114_gen019"
  },
  {
    "question_text": "Define an elementary event in the context of probability theory.",
    "type": "Short Answer",
    "difficulty": "Easy",
    "options": null,
    "correct_answer": "An elementary event is a singleton set consisting of a single outcome from the sample space.",
    "explanation": "An elementary event refers to an event that contains exactly one outcome. It is denoted as {ω} for some ω in the sample space S. This concept is used for notational convenience where P(ω) stands in for P({ω}).",
    "topic": "Basic Definitions",
    "bloom_level": "Remember",
    "source": "generated",
    "chapter_id": "kemh114",
    "section_id": "04_section_14_2",
    "question_id": "cbse_xi_kemh1dd_c114_gen020"
  },
  {
    "question_text": "State the three fundamental axioms of probability.",
    "type": "Short Answer",
    "difficulty": "Medium",
    "options": null,
    "correct_answer": "1) For any event E, P(E) ≥ 0. 2) P(S) = 1 where S is the sample space. 3) For mutually exclusive events E and F, P(E ∪ F) = P(E) + P(F).",
    "explanation": "The axioms of probability form the foundation of probability theory. They are: (i) non-negativity (each event has a probability of at least 0), (ii) normalization (the probability of the entire sample space is 1), and (iii) additivity (for mutually exclusive events, the probability of their union is the sum of their individual probabilities).",
    "topic": "Axiomatic Approach to Probability",
    "bloom_level": "Remember",
    "source": "generated",
    "chapter_id": "kemh114",
    "section_id": "04_section_14_2",
    "question_id": "cbse_xi_kemh1dd_c114_gen021"
  },
  {
    "question_text": "Explain the concept of 'Probability of not A' and how it is calculated.",
    "type": "Short Answer",
    "difficulty": "Easy",
    "options": null,
    "correct_answer": "The probability of 'not A', denoted as P(A'), is calculated as 1 - P(A).",
    "explanation": "Since A and A' are mutually exclusive and their union is the whole sample space S, we have P(A) + P(A') = 1. Hence, P(A') = 1 - P(A).",
    "topic": "Complementary Events",
    "bloom_level": "Understand",
    "source": "generated",
    "chapter_id": "kemh114",
    "section_id": "04_section_14_2",
    "question_id": "cbse_xi_kemh1dd_c114_gen022"
  },
  {
    "question_text": "What does it mean when outcomes of a sample space are 'equally likely'? Explain briefly.",
    "type": "Short Answer",
    "difficulty": "Medium",
    "options": null,
    "correct_answer": "Outcomes are equally likely when each outcome has the same probability of occurring, typically defined as p = 1/n if there are n outcomes.",
    "explanation": "When outcomes are equally likely, it implies that there is no bias toward any outcome. Thus, the probability assigned to each outcome in the sample space is identical, and the total probability sums up to 1.",
    "topic": "Equally Likely Outcomes",
    "bloom_level": "Understand",
    "source": "generated",
    "chapter_id": "kemh114",
    "section_id": "04_section_14_2",
    "question_id": "cbse_xi_kemh1dd_c114_gen023"
  },
  {
    "question_text": "Prove that for any two events A and B, the probability of their union is given by P(A ∪ B) = P(A) + P(B) - P(A ∩ B).",
    "type": "Long Answer",
    "difficulty": "Hard",
    "options": null,
    "correct_answer": "Starting with A ∪ B = (A - B) ∪ (A ∩ B) ∪ (B - A), and since these sets are mutually exclusive, we have P(A ∪ B) = P(A - B) + P(A ∩ B) + P(B - A). Notice that P(A) = P(A - B) + P(A ∩ B) and P(B) = P(B - A) + P(A ∩ B). Adding these, P(A) + P(B) = P(A - B) + P(B - A) + 2P(A ∩ B). Subtracting P(A ∩ B) from both sides gives the formula P(A ∪ B) = P(A) + P(B) - P(A ∩ B).",
    "explanation": "Step 1: Decompose A and B: A = (A - B) ∪ (A ∩ B) and B = (B - A) ∪ (A ∩ B). \nStep 2: Recognize that (A - B), (B - A), and (A ∩ B) are mutually exclusive. \nStep 3: Write P(A) = P(A - B) + P(A ∩ B) and P(B) = P(B - A) + P(A ∩ B). \nStep 4: Therefore, P(A ∪ B) = P(A - B) + P(A ∩ B) + P(B - A). \nStep 5: Summing P(A) and P(B) and subtracting P(A ∩ B) yields the required result.",
    "topic": "Addition Rule of Probability",
    "bloom_level": "Create",
    "source": "generated",
    "chapter_id": "kemh114",
    "section_id": "04_section_14_2",
    "question_id": "cbse_xi_kemh1dd_c114_gen024"
  },
  {
    "question_text": "Derive the expression for the probability of an event E when outcomes are equally likely in a finite sample space S with n outcomes and event E contains m outcomes.",
    "type": "Long Answer",
    "difficulty": "Medium",
    "options": null,
    "correct_answer": "When outcomes are equally likely, each outcome has probability 1/n. For an event E containing m outcomes, the probability is P(E) = m/n.",
    "explanation": "Step 1: Under equally likely conditions, assign each outcome a probability of 1/n. \nStep 2: Since an event E is a collection of m outcomes, by the additivity property, P(E) = m × (1/n) = m/n.",
    "topic": "Equally Likely Outcomes",
    "bloom_level": "Apply",
    "source": "generated",
    "chapter_id": "kemh114",
    "section_id": "04_section_14_2",
    "question_id": "cbse_xi_kemh1dd_c114_gen025"
  },
  {
    "question_text": "Using the axioms of probability, prove that the probability of the empty event (φ) is 0.",
    "type": "Long Answer",
    "difficulty": "Hard",
    "options": null,
    "correct_answer": "Let E be any event and let F = φ (the empty set). Since E and φ are mutually exclusive, by axiom (iii), P(E ∪ φ) = P(E) + P(φ). But since E ∪ φ = E, we obtain P(E) = P(E) + P(φ). Subtracting P(E) from both sides gives P(φ) = 0.",
    "explanation": "Step 1: Consider any event E and the empty set φ. \nStep 2: Since E and φ have no common elements, they are mutually exclusive. \nStep 3: By the additivity axiom, P(E ∪ φ) = P(E) + P(φ). \nStep 4: Noting that E ∪ φ = E, we have P(E) = P(E) + P(φ). \nStep 5: Subtract P(E) from both sides to deduce P(φ) = 0.",
    "topic": "Axiomatic Proofs",
    "bloom_level": "Evaluate",
    "source": "generated",
    "chapter_id": "kemh114",
    "section_id": "04_section_14_2",
    "question_id": "cbse_xi_kemh1dd_c114_gen026"
  },
  {
    "question_text": "A bag contains 9 discs: 4 red, 3 blue, and 2 yellow. If a disc is drawn at random, calculate the probability that: (i) the disc is red, (ii) the disc is yellow, (iii) the disc is blue, (iv) the disc is not blue, and (v) the disc is either red or blue.",
    "type": "Numerical",
    "difficulty": "Medium",
    "options": null,
    "correct_answer": "(i) P(red) = 4/9. (ii) P(yellow) = 2/9. (iii) P(blue) = 3/9 = 1/3. (iv) P(not blue) = 1 - 1/3 = 2/3. (v) P(red or blue) = (4 + 3)/9 = 7/9.",
    "explanation": "Total discs = 9. \n(i) Red = 4 discs, so P(red) = 4/9. \n(ii) Yellow = 2 discs, so P(yellow) = 2/9. \n(iii) Blue = 3 discs, so P(blue) = 3/9 = 1/3. \n(iv) P(not blue) = 1 - P(blue) = 1 - 1/3 = 2/3. \n(v) Red or blue, since these events are mutually exclusive, P(red or blue) = P(red) + P(blue) = 4/9 + 3/9 = 7/9.",
    "topic": "Probability of an Event",
    "bloom_level": "Apply",
    "source": "generated",
    "chapter_id": "kemh114",
    "section_id": "04_section_14_2",
    "question_id": "cbse_xi_kemh1dd_c114_gen027"
  },
  {
    "question_text": "One card is drawn from a well-shuffled deck of 52 cards. Calculate the probabilities that the card drawn is: (i) a diamond, (ii) not an ace, (iii) a black card, (iv) not a diamond, and (v) not a black card.",
    "type": "Numerical",
    "difficulty": "Medium",
    "options": null,
    "correct_answer": "(i) P(diamond) = 13/52 = 1/4; (ii) P(not an ace) = 1 - 4/52 = 12/13; (iii) P(black) = 26/52 = 1/2; (iv) P(not a diamond) = 1 - 1/4 = 3/4; (v) P(not a black card) = 1 - 1/2 = 1/2.",
    "explanation": "In a 52-card deck, there are 13 diamonds, 4 aces, and 26 black cards (clubs and spades). \n(i) P(diamond) = 13/52 = 1/4. \n(ii) P(ace) = 4/52 so P(not an ace) = 1 - 4/52 = 48/52 = 12/13. \n(iii) P(black) = 26/52 = 1/2. \n(iv) P(not a diamond) = 1 - 1/4 = 3/4. \n(v) P(not a black card) = 1 - 1/2 = 1/2.",
    "topic": "Card Probability",
    "bloom_level": "Apply",
    "source": "generated",
    "chapter_id": "kemh114",
    "section_id": "04_section_14_2",
    "question_id": "cbse_xi_kemh1dd_c114_gen028"
  },
  {
    "question_text": "Two students, Anil and Ashima, have probabilities of qualifying an exam as 0.05 and 0.10 respectively, with P(both qualify) = 0.02. Calculate the probability that: (a) both do not qualify, (b) at least one does not qualify, and (c) exactly one qualifies.",
    "type": "Numerical",
    "difficulty": "Medium",
    "options": null,
    "correct_answer": "(a) P(neither qualifies) = 1 - [0.05 + 0.10 - 0.02] = 0.87; (b) P(at least one does not qualify) = 1 - 0.02 = 0.98; (c) P(exactly one qualifies) = (0.05 - 0.02) + (0.10 - 0.02) = 0.11.",
    "explanation": "Let E = event Anil qualifies and F = event Ashima qualifies. \n(a) P(neither qualifies) = P(E' ∩ F') = 1 - P(E ∪ F) where P(E ∪ F) = 0.05 + 0.10 - 0.02 = 0.13. Therefore, 1 - 0.13 = 0.87. \n(b) At least one does not qualify = 1 - P(both qualify) = 1 - 0.02 = 0.98. \n(c) Exactly one qualifies = [P(E) - P(E ∩ F)] + [P(F) - P(E ∩ F)] = (0.05 - 0.02) + (0.10 - 0.02) = 0.11.",
    "topic": "Combined Event Probability",
    "bloom_level": "Analyze",
    "source": "generated",
    "chapter_id": "kemh114",
    "section_id": "04_section_14_2",
    "question_id": "cbse_xi_kemh1dd_c114_gen029"
  },
  {
    "question_text": "From a group consisting of 2 men and 2 women, a committee of 2 persons is to be selected. Calculate the probability that the committee has: (a) no man, (b) exactly one man, and (c) two men.",
    "type": "Numerical",
    "difficulty": "Medium",
    "options": null,
    "correct_answer": "(a) P(no man) = 1/6; (b) P(exactly one man) = 2/3; (c) P(two men) = 1/6.",
    "explanation": "Total ways to select 2 persons from 4 = ⁴C₂ = 6. \n(a) No man means both are women: ²C₂ = 1 way → P = 1/6. \n(b) Exactly one man: choose 1 man from 2 and 1 woman from 2: ²C₁ × ²C₁ = 4 ways → P = 4/6 = 2/3. \n(c) Two men: ²C₂ = 1 way → P = 1/6.",
    "topic": "Combinatorial Probability",
    "bloom_level": "Apply",
    "source": "generated",
    "chapter_id": "kemh114",
    "section_id": "04_section_14_2",
    "question_id": "cbse_xi_kemh1dd_c114_gen030"
  }
]